{
  "url": "https://www.formula1.com/en/racing/2026/japan",
  "updatedAt": "2026-01-19T14:43:34.324Z",
  "nameFull": "FORMULA 1 ARAMCO JAPANESE GRAND PRIX 2026",
  "nameMedium": "Japanese Grand Prix",
  "data": [
    {
      "name": "Practice 1",
      "localDate": "2026-03-27",
      "localStartTime": "11:30",
      "localEndTime": "12:30"
    },
    {
      "name": "Practice 2",
      "localDate": "2026-03-27",
      "localStartTime": "15:00",
      "localEndTime": "16:00"
    },
    {
      "name": "Practice 3",
      "localDate": "2026-03-28",
      "localStartTime": "11:30",
      "localEndTime": "12:30"
    },
    {
      "name": "Qualifying",
      "localDate": "2026-03-28",
      "localStartTime": "15:00",
      "localEndTime": "16:00"
    },
    {
      "name": "Race",
      "localDate": "2026-03-29",
      "localStartTime": "14:00",
      "localEndTime": null
    }
  ]
}